MANIFEST.in
README.md
setup.py
thing/__init__.py
thing/thing.py
thing.egg-info/PKG-INFO
thing.egg-info/SOURCES.txt
thing.egg-info/dependency_links.txt
thing.egg-info/not-zip-safe
thing.egg-info/requires.txt
thing.egg-info/top_level.txt