Metadata-Version: 1.0
Name: thing
Version: 0.3.3
Summary: lightweight SQLAlchemy based ORM
Home-page: http://github.com/lzyy/thing
Author: lzyy
Author-email: healdream@gmail.com
License: BSD
Platform: any
Classifier: Development Status :: 4 - Beta
Classifier: Intended Audience :: Developers
Classifier: License :: OSI Approved :: BSD License
Classifier: Operating System :: OS Independent
Classifier: Programming Language :: Python
Classifier: Topic :: Database
Classifier: Topic :: Software Development :: Libraries :: Python Modules
